CTDbscan/CTDBSCAN.py
CTDbscan/__init__.py
CTDbscan-1.0.0.dist-info/LICENSE
CTDbscan-1.0.0.dist-info/METADATA
CTDbscan-1.0.0.dist-info/WHEEL
CTDbscan-1.0.0.dist-info/top_level.txt
CTDbscan-1.0.0.dist-info/RECORD
