Metadata-Version: 2.1
Name: CTDbscan
Version: 1.0.0
Summary: Spatial clustering of continuous trajectories
Author: Junlang Li
Author-email: lijunlang1123@163.com
Classifier: Programming Language :: Python :: 3
Classifier: License :: OSI Approved :: MIT License
Classifier: Operating System :: OS Independent
License-File: LICENSE
Requires-Dist: pandas (>=1.5.2)
